Metadata-Version: 2.1
Name: ReportMiner
Version: 0.1.3
Summary: Easy to use wrapper for text document question and answer using RAG and LLM
Home-page: https://github.com/yohanesnuwara/reportminer
Author: Yohanes Nuwara
Author-email: ign.nuwara97@gmail.com
License: MIT License
Classifier: Development Status :: 1 - Planning
Classifier: Intended Audience :: Developers
Classifier: License :: OSI Approved :: MIT License
Classifier: Operating System :: POSIX :: Linux
Classifier: Programming Language :: Python :: 3.10
License-File: LICENSE
Requires-Dist: byaldi>=0.0.7
Requires-Dist: transformers>=4.46.3
Requires-Dist: pdf2image>=1.17.0
Requires-Dist: pillow>=11.1.0
Requires-Dist: numpy>=1.26.4
Requires-Dist: matplotlib>=3.10.0
Requires-Dist: pypdf2>=3.0.1
